{
    "@id": "dtmi:com:vehicle:body:light;1",
    "@type": "Interface",
    "comment": "All exterior lights",
    "displayName": "Lights",
    "contents": [
    {
        "@type": "Property",
        "name": "HighBeam",
        "description": "High beam lights on or off. True = On. False = Off.",
        "comment": "actuator",
        "schema": "boolean"
    },
    {
        "@type": "Property",
        "name": "LowBeam",
        "description": "Low beam lights on or off. True = On. False = Off.",
        "comment": "actuator",
        "schema": "boolean"
    },
    {
        "@type": "Property",
        "name": "Running",
        "description": "Running lights on or off. True = On. False = Off.",
        "comment": "actuator",
        "schema": "boolean"
    },
    {
        "@type": "Property",
        "name": "Backup",
        "description": "Backup (reverse) lights on or off. True = On. False = Off.",
        "comment": "actuator",
        "schema": "boolean"
    },
    {
        "@type": "Property",
        "name": "Parking",
        "description": "Parking lights on or off. True = On. False = Off.",
        "comment": "actuator",
        "schema": "boolean"
    },
    {
        "@type": "Property",
        "name": "Brake",
        "description": "Brake lights on or off. True = On. False = Off.",
        "comment": "actuator",
        "schema": "boolean"
    },
    {
        "@type": "Property",
        "name": "RearFog",
        "description": "Rear fog lights on or off. True = On. False = Off.",
        "comment": "actuator",
        "schema": "boolean"
    },
    {
        "@type": "Property",
        "name": "FrontFog",
        "description": "Front fog lights on or off. True = On. False = Off.",
        "comment": "actuator",
        "schema": "boolean"
    },
    {
        "@type": "Property",
        "name": "Hazard",
        "description": "Hazard lights on or off. True = On. False = Off.",
        "comment": "actuator",
        "schema": "boolean"
    },
    {
        "@type": "Property",
        "name": "LeftIndicator",
        "description": "Left indicator lights on or off. True = On. False = Off.",
        "comment": "actuator",
        "schema": "boolean"
    },
    {
        "@type": "Property",
        "name": "RightIndicator",
        "description": "Right indicator lights on or off. True = On. False = Off.",
        "comment": "actuator",
        "schema": "boolean"
    }
    ],
    "@context": "dtmi:dtdl:context;2"
  }